pytest_network_endpoints/__init__.py
pytest_network_endpoints/plugin.py
pytest_network_endpoints/snmp.py
pytest_network_endpoints/ssh.py
pytest_network_endpoints/tunnel.py
pytest_network_endpoints/winrm.py
pytest_network_endpoints-0.0.4.dist-info/METADATA
pytest_network_endpoints-0.0.4.dist-info/WHEEL
pytest_network_endpoints-0.0.4.dist-info/entry_points.txt
pytest_network_endpoints-0.0.4.dist-info/top_level.txt
pytest_network_endpoints-0.0.4.dist-info/RECORD
